dbnomics_data_model/__init__.py
dbnomics_data_model/errors.py
dbnomics_data_model/model/__init__.py
dbnomics_data_model/model/attributes.py
dbnomics_data_model/model/category_tree.py
dbnomics_data_model/model/common.py
dbnomics_data_model/model/dataset_metadata.py
dbnomics_data_model/model/dimensions.py
dbnomics_data_model/model/merge_utils.py
dbnomics_data_model/model/periods.py
dbnomics_data_model/model/provider_metadata.py
dbnomics_data_model/model/releases_metadata.py
dbnomics_data_model/model/series.py
dbnomics_data_model/py.typed
dbnomics_data_model/scripts/update_storage.py
dbnomics_data_model/scripts/validate_storage.py
dbnomics_data_model/storage/__init__.py
dbnomics_data_model/storage/adapters/__init__.py
dbnomics_data_model/storage/adapters/filesystem/__init__.py
dbnomics_data_model/storage/adapters/filesystem/file_utils.py
dbnomics_data_model/storage/adapters/filesystem/model/__init__.py
dbnomics_data_model/storage/adapters/filesystem/model/base_dataset_json.py
dbnomics_data_model/storage/adapters/filesystem/model/base_series_json.py
dbnomics_data_model/storage/adapters/filesystem/model/category_tree_json.py
dbnomics_data_model/storage/adapters/filesystem/model/json_lines_variant/__init__.py
dbnomics_data_model/storage/adapters/filesystem/model/json_lines_variant/json_lines_dataset_json.py
dbnomics_data_model/storage/adapters/filesystem/model/json_lines_variant/json_lines_series_item.py
dbnomics_data_model/storage/adapters/filesystem/model/observations.py
dbnomics_data_model/storage/adapters/filesystem/model/tsv_variant/__init__.py
dbnomics_data_model/storage/adapters/filesystem/model/tsv_variant/tsv_dataset_json.py
dbnomics_data_model/storage/adapters/filesystem/model/tsv_variant/tsv_series_json.py
dbnomics_data_model/storage/adapters/filesystem/storage.py
dbnomics_data_model/storage/adapters/filesystem/storage_pool.py
dbnomics_data_model/storage/adapters/filesystem/tsv_utils.py
dbnomics_data_model/storage/errors.py
dbnomics_data_model-0.13.35.dist-info/entry_points.txt
dbnomics_data_model-0.13.35.dist-info/LICENSE
dbnomics_data_model-0.13.35.dist-info/WHEEL
dbnomics_data_model-0.13.35.dist-info/METADATA
dbnomics_data_model-0.13.35.dist-info/RECORD
