Metadata-Version: 2.1
Name: dbnomics-data-model
Version: 0.13.35
Summary: Provide classes for DBnomics entities and a storage abstraction
Home-page: https://git.nomics.world/dbnomics/dbnomics-data-model
License: AGPL-3.0-or-later
Author: DBnomics Team
Author-email: contact@nomics.world
Requires-Python: >=3.7,<4.0
Classifier: License :: OSI Approved :: GNU Affero General Public License v3 or later (AGPLv3+)
Classifier: Programming Language :: Python :: 3
Classifier: Programming Language :: Python :: 3.7
Classifier: Programming Language :: Python :: 3.8
Classifier: Programming Language :: Python :: 3.9
Classifier: Programming Language :: Python :: 3.10
Classifier: Programming Language :: Python :: 3.11
Requires-Dist: daiquiri (>=3.0.1,<4.0.0)
Requires-Dist: dirsync (>=2.2.5,<3.0.0)
Requires-Dist: jsonschema (>=4.4.0,<5.0.0)
Requires-Dist: orjson (>=3.6.7,<4.0.0)
Requires-Dist: pydantic (>=1.9.0,<2.0.0)
Requires-Dist: pysimdjson (>=4.0.3,<5.0.0)
Requires-Dist: python-dateutil (>=2.8.2,<3.0.0)
Requires-Dist: pyyaml (>=6.0,<7.0)
Requires-Dist: toolz (>=0.11.2,<0.12.0)
Requires-Dist: typer[all] (>=0.7.0,<0.8.0)
Project-URL: Repository, https://git.nomics.world/dbnomics/dbnomics-data-model
